render_swiper/__init__.py
render_swiper/definitions.py
render_swiper/js/01e8ad0f37de64e3ddcb.275.js
render_swiper/js/034546b0939034d83052.770.js
render_swiper/js/0c4d66e44131dffcf235.751.js
render_swiper/js/26817e1d925def0f7b11.43.js
render_swiper/js/2ed3a3a9d2b1c5e41979.24.js
render_swiper/js/48d207d789cfcf1d5083.652.js
render_swiper/js/6fbd758ef6827c121340.43.js
render_swiper/js/73934db5a20c914cfff7.989.js
render_swiper/js/7b1e66e34bef5c4200e0.830.js
render_swiper/js/7c7c11d28f36a8275f8c.989.js
render_swiper/js/822c67d9e297465ec98b.24.js
render_swiper/js/853922409b0ecd163f2c.751.js
render_swiper/js/8ab3465551771204d1c1.751.js
render_swiper/js/9bbc91cadc7e974ab058.624.js
render_swiper/js/bd76aa86f0dde95ebd85.737.js
render_swiper/js/c78fecd6786bd8dc0ced.751.js
render_swiper/js/d29ad71377a2c38f84eb.737.js
render_swiper/js/dec6ce8c0e7c1e479190.652.js
render_swiper/js/e4452090f44af91f5d6c.652.js
render_swiper/js/eab3bba9e382a2c00ecf.652.js
render_swiper/js/fa1e8f5020fd7c830643.58.js
render_swiper/js/fa1e8f5020fd7c830643.58.js.LICENSE.txt
render_swiper/js/index.js
render_swiper-0.6.0.dist-info/METADATA
render_swiper-0.6.0.dist-info/WHEEL
render_swiper-0.6.0.dist-info/RECORD
